spoc/__about__.py
spoc/__init__.py
spoc/case_style.py
spoc/components.py
spoc/framework.py
spoc/inject_apps.py
spoc/tools.py
spoc/types.py
spoc/workers.py
spoc/core/__init__.py
spoc/core/config_loader.py
spoc/core/exceptions.py
spoc/core/importer.py
spoc/core/logging_utils.py
spoc/core/singleton.py
spoc/core/toml_core.py
spoc/core/utils.py
spoc-0.3.0.dist-info/METADATA
spoc-0.3.0.dist-info/WHEEL
spoc-0.3.0.dist-info/licenses/LICENSE
spoc-0.3.0.dist-info/RECORD
