Metadata-Version: 2.4
Name: spoc
Version: 0.3.0
Summary: Elastic Framework Builder
Author-email: hlop3z <23062270+hlop3z@users.noreply.github.com>
License-File: LICENSE
Requires-Python: >=3.13
